wynntilsresolver/__init__.py
wynntilsresolver/blocks/__init__.py
wynntilsresolver/blocks/block.py
wynntilsresolver/blocks/end.py
wynntilsresolver/blocks/identification.py
wynntilsresolver/blocks/name.py
wynntilsresolver/blocks/powder.py
wynntilsresolver/blocks/reroll.py
wynntilsresolver/blocks/shiny.py
wynntilsresolver/blocks/type.py
wynntilsresolver/blocks/version.py
wynntilsresolver/exception.py
wynntilsresolver/item.py
wynntilsresolver/py.typed
wynntilsresolver/resolver.py
wynntilsresolver/resource.py
wynntilsresolver/startup.py
wynntilsresolver/utils.py
wynntilsresolver-1.4.1.dist-info/WHEEL
wynntilsresolver-1.4.1.dist-info/METADATA
wynntilsresolver-1.4.1.dist-info/RECORD
