Metadata-Version: 2.4
Name: wynntilsresolver
Version: 1.4.1
Summary: A simple resolver to analyze wynntils' encoded equipment in chat.
Keywords: wynntils,resolver,wynncraft
Author: FYWinds
Author-email: FYWinds <i@windis.cn>
License-Expression: MIT
Classifier: Programming Language :: Python :: 3.8
Classifier: Programming Language :: Python :: 3.9
Classifier: Programming Language :: Python :: 3.10
Classifier: Programming Language :: Python :: 3.11
Classifier: Programming Language :: Python :: 3.12
Requires-Dist: httpx==0.27.0
Requires-Dist: pytest==8.0.2 ; extra == 'test'
Requires-Dist: pytest-cov==4.1.0 ; extra == 'test'
Requires-Dist: pytest-xdist==3.5.0 ; extra == 'test'
Requires-Python: >=3.8
Project-URL: Changelog, https://github.com/fywinds/WynntilsResolver
Project-URL: Documentation, https://github.com/fywinds/WynntilsResolver
Project-URL: Homepage, https://github.com/fywinds/WynntilsResolver
Project-URL: Repository, https://github.com/fywinds/WynntilsResolver
Provides-Extra: test
